moss_cappa/__init__.py
moss_cappa/moss.py
moss_cappa-0.3.dist-info/LICENSE
moss_cappa-0.3.dist-info/METADATA
moss_cappa-0.3.dist-info/WHEEL
moss_cappa-0.3.dist-info/top_level.txt
moss_cappa-0.3.dist-info/RECORD
