Metadata-Version: 2.1
Name: moss_cappa
Version: 0.3
Summary: Python-клиент Moss, предназначенный для использования в комплексе автоматической проверки программ CAPPA
Home-page: https://github.com/Shroud007/moss_cappa
Download-URL: https://github.com/Shroud007/moss_cappa/releases
Author: shroud007
Keywords: cappa,moss,plagiarism
License-File: LICENSE
Requires-Dist: beautifulsoup4
Requires-Dist: lxml
